{
  "slug": "dia",
  "name": "Dia",
  "category": "platforms",
  "description": "AI-powered web browser by The Browser Company that surfaces answers and generates ready-to-share outputs from browser tabs.",
  "tags": ["browser", "ai-browser", "chromium", "web-browsing", "tab-management", "ai-assistant", "macos", "productivity-tools"],
  "brandColor": "#4566B7",
  "url": "https://www.diabrowser.com",
  "license": "Trademark — usage for identification (fair use)",
  "latest": "2025",
  "years": [
    {
      "year": "2024",
      "palette": ["#E68163"],
      "source": "https://web.archive.org/web/20241202084233/https://www.diabrowser.com/",
      "notes": "Launch teaser mark (December 2024). Orange sun-rising symbol used on the pre-launch page."
    },
    {
      "year": "2025",
      "palette": ["#4566B7", "#6D9FE4", "#C5D8E8", "#E1E7DB", "#F5E48C", "#FBC95E", "#F59058"],
      "source": "https://img.alternativeto.net/icons/280/dia-browser_257206.png",
      "notes": "Gradient dome mark (blue-to-orange vertical gradient on transparent canvas)."
    }
  ],
  "addedAt": "2026-05-23",
  "updatedAt": "2026-05-23"
}
